klipper_repl/__init__.py
klipper_repl/api.py
klipper_repl/cli.py
klipper_repl/lexer.py
klipper_repl/output.py
klipper_repl-0.2.0.dist-info/COPYING
klipper_repl-0.2.0.dist-info/METADATA
klipper_repl-0.2.0.dist-info/WHEEL
klipper_repl-0.2.0.dist-info/entry_points.txt
klipper_repl-0.2.0.dist-info/RECORD
