Metadata-Version: 2.1
Name: klipper-repl
Version: 0.2.0
Summary: The missing Klipper command line
Author: Jordan Mulcahey
Author-email: snhjordy@gmail.com
Requires-Python: >=3.10,<4.0
Classifier: Programming Language :: Python :: 3
Classifier: Programming Language :: Python :: 3.10
Classifier: Programming Language :: Python :: 3.11
Requires-Dist: prompt-toolkit (>=3.0.38,<4.0.0)
Requires-Dist: pygments (>=2.15.1,<3.0.0)
